deutschland/lebensmittelwarnung/__init__.py
deutschland/lebensmittelwarnung/api/__init__.py
deutschland/lebensmittelwarnung/api/default_api.py
deutschland/lebensmittelwarnung/api_client.py
deutschland/lebensmittelwarnung/apis/__init__.py
deutschland/lebensmittelwarnung/configuration.py
deutschland/lebensmittelwarnung/exceptions.py
deutschland/lebensmittelwarnung/model/__init__.py
deutschland/lebensmittelwarnung/model/inline_object.py
deutschland/lebensmittelwarnung/model/request_options.py
deutschland/lebensmittelwarnung/model/response.py
deutschland/lebensmittelwarnung/model/response_docs.py
deutschland/lebensmittelwarnung/model/response_product.py
deutschland/lebensmittelwarnung/model/response_rapex_information.py
deutschland/lebensmittelwarnung/model/response_safety_information.py
deutschland/lebensmittelwarnung/model_utils.py
deutschland/lebensmittelwarnung/models/__init__.py
deutschland/lebensmittelwarnung/rest.py
de_lebensmittelwarnung-0.1.0.dist-info/WHEEL
de_lebensmittelwarnung-0.1.0.dist-info/METADATA
de_lebensmittelwarnung-0.1.0.dist-info/RECORD
